cortecs/__init__.py
cortecs/eval/__init__.py
cortecs/eval/eval.py
cortecs/eval/eval_neural_net.py
cortecs/eval/eval_pca.py
cortecs/eval/eval_polynomial.py
cortecs/fit/__init__.py
cortecs/fit/fit.py
cortecs/fit/fit_neural_net.py
cortecs/fit/fit_pca.py
cortecs/fit/fit_polynomial.py
cortecs/fit/metrics.py
cortecs/opac/__init__.py
cortecs/opac/chunking.py
cortecs/opac/interpolate_cia.py
cortecs/opac/io.py
cortecs/opac/opac.py
"cortecs/opt/__init__,py"
cortecs/opt/opt.py
cortecs/opt/optimize_neural_net.py
cortecs/opt/optimize_pca.py
cortecs/opt/optimize_polynomial.py
cortecs/tests/absorb_coeffs_C2H4.npy
cortecs/tests/opacCH4_narrow_wl.dat
cortecs/tests/pressures.npy
cortecs/tests/temperatures.npy
cortecs/tests/test_chunking.py
cortecs/tests/test_eval.py
cortecs/tests/test_fit.py
cortecs/tests/test_integration.py
cortecs/tests/test_opac.py
cortecs/tests/test_opac_cia.dat
cortecs/tests/test_pca_coeffs.npy
cortecs/tests/test_pca_vectors.npy
cortecs/tests/wavelengths.npy
cortecs-1.0.1.dist-info/LICENSE
cortecs-1.0.1.dist-info/METADATA
cortecs-1.0.1.dist-info/WHEEL
cortecs-1.0.1.dist-info/top_level.txt
cortecs-1.0.1.dist-info/RECORD
