Metadata-Version: 2.1
Name: cortecs
Version: 1.0.1
Summary: Compress opacity for radiative transfer
Author: Megan Bedell, Eliza M.-R. Kempton
Author-email: Arjun Savel <asavel@umd.edu>
License: MIT
Project-URL: Homepage, https://github.com/arjunsavel/cortecs
Project-URL: Issues, https://github.com/arjunsavel/cortecs/issues
Project-URL: Documentation, https://cortecs.readthedocs.io
Keywords: astronomy
Classifier: Development Status :: 4 - Beta
Classifier: Intended Audience :: Developers
Classifier: Intended Audience :: Science/Research
Classifier: Natural Language :: English
Classifier: License :: OSI Approved :: MIT License
Classifier: Programming Language :: Python
Classifier: Programming Language :: Python :: 3.8
Classifier: Programming Language :: Python :: 3.9
Classifier: Programming Language :: Python :: 3.10
Classifier: Programming Language :: Python :: 3.11
Classifier: Topic :: Scientific/Engineering :: Astronomy
Requires-Python: >=3.8
License-File: LICENSE
Requires-Dist: numpy
Requires-Dist: jaxlib
Requires-Dist: jax
Requires-Dist: tqdm
Requires-Dist: h5py
Requires-Dist: matplotlib
Requires-Dist: pandas
Provides-Extra: neural_networks
Requires-Dist: tensorflow <=2.15.0.post1 ; extra == 'neural_networks'
Requires-Dist: keras ; extra == 'neural_networks'
